qiskit_inspect/__init__.py
qiskit_inspect/_version_guard.py
qiskit_inspect/analytics.py
qiskit_inspect/assertions.py
qiskit_inspect/backend_trace.py
qiskit_inspect/debugger.py
qiskit_inspect/export.py
qiskit_inspect/prefix_builders.py
qiskit_inspect/probabilities.py
qiskit_inspect/py.typed
qiskit_inspect/sampler_results.py
qiskit_inspect/trace_logging.py
qiskit_inspect/visual.py
qiskit_inspect-0.1.1.dist-info/licenses/LICENSE
qiskit_inspect-0.1.1.dist-info/METADATA
qiskit_inspect-0.1.1.dist-info/WHEEL
qiskit_inspect-0.1.1.dist-info/top_level.txt
qiskit_inspect-0.1.1.dist-info/RECORD
