Metadata-Version: 2.4
Name: qiskit-inspect
Version: 0.1.1
Summary: Debugger, backend prefix tracing, and assertions for Qiskit
Author-email: Soumyadip Sarkar <soumyadip@soumyadipsarkar.com>
License-Expression: Apache-2.0
Project-URL: homepage, https://github.com/neuralsorcerer/qiskit-inspect
Keywords: qiskit,quantum,debugger,statevector,probabilities,testing
Classifier: Intended Audience :: Developers
Classifier: Intended Audience :: Science/Research
Classifier: Programming Language :: Python
Classifier: Programming Language :: Python :: 3
Classifier: Programming Language :: Python :: 3.10
Classifier: Programming Language :: Python :: 3.11
Classifier: Programming Language :: Python :: 3.12
Classifier: Programming Language :: Python :: 3.13
Classifier: Topic :: Scientific/Engineering
Classifier: Topic :: Software Development :: Testing
Requires-Python: >=3.10
License-File: LICENSE
Requires-Dist: numpy>=1.24
Requires-Dist: qiskit>=2.0
Provides-Extra: data
Requires-Dist: pandas>=1.5; extra == "data"
Provides-Extra: aer
Requires-Dist: qiskit-aer>=0.14; extra == "aer"
Provides-Extra: runtime
Requires-Dist: qiskit-ibm-runtime>=0.40; extra == "runtime"
Provides-Extra: visualization
Requires-Dist: matplotlib>=3.7; extra == "visualization"
Requires-Dist: seaborn>=0.12; extra == "visualization"
Provides-Extra: dev
Requires-Dist: pytest; extra == "dev"
Requires-Dist: pytest-cov; extra == "dev"
Requires-Dist: mypy; extra == "dev"
Requires-Dist: isort; extra == "dev"
Requires-Dist: black; extra == "dev"
Requires-Dist: pre-commit; extra == "dev"
Requires-Dist: pandas>=1.5; extra == "dev"
Requires-Dist: qiskit-aer>=0.14; extra == "dev"
Requires-Dist: qiskit-ibm-runtime>=0.40; extra == "dev"
Requires-Dist: matplotlib>=3.7; extra == "dev"
Requires-Dist: seaborn>=0.12; extra == "dev"
Dynamic: license-file
